lembed/__init__.py
lembed/lembed.py
lembed-0.1.0.dist-info/METADATA
lembed-0.1.0.dist-info/WHEEL
lembed-0.1.0.dist-info/top_level.txt
lembed-0.1.0.dist-info/RECORD
