Metadata-Version: 2.4
Name: lembed
Version: 0.1.0
Summary: Python extension to embed live webpages with PyQt6.
Author: Shanveer Singh Sodha
Requires-Python: >=3.6
Requires-Dist: PyQt6
Requires-Dist: PyQt6-WebEngine
Dynamic: author
Dynamic: requires-dist
Dynamic: requires-python
Dynamic: summary
